demo/demo_push_request_huaweicloud.py
demo/demo_push_request_local_qwq.py
demo/demo_push_stream_huaweicloud.py
demo/demo_push_stream_local_qwq.py
llm_repeator_redis/__init__.py
llm_repeator_redis/arch_worker_main.py
llm_repeator_redis/llm_worker_main.py
llm_repeator_redis/arch_services/__init__.py
llm_repeator_redis/arch_services/arch_worker.py
llm_repeator_redis/llm_services/__init__.py
llm_repeator_redis/llm_services/llm_resources_manager.py
llm_repeator_redis/llm_services/llm_response.py
llm_repeator_redis/llm_services/llm_worker.py
llm_repeator_redis/ollama_services/__init__.py
llm_repeator_redis/ollama_services/ollama_tools.py
llm_repeator_redis/redis_services/__init__.py
llm_repeator_redis/redis_services/redis_read_manager.py
llm_repeator_redis/tools/__init__.py
llm_repeator_redis/tools/init_tools.py
llm_repeator_redis/tools/time_controller.py
llm_repeator_redis-0.1.16.dist-info/METADATA
llm_repeator_redis-0.1.16.dist-info/WHEEL
llm_repeator_redis-0.1.16.dist-info/entry_points.txt
llm_repeator_redis-0.1.16.dist-info/top_level.txt
llm_repeator_redis-0.1.16.dist-info/RECORD
