Metadata-Version: 2.4
Name: llm_repeator_redis
Version: 0.1.16
Summary: LLM tools for repeated generation
Author-email: Fang JiaWei <fjw12998@hotmail.com>
License-Expression: GPL-3.0-or-later
Project-URL: Homepage, https://gitee.com/sky_flash/llm_repeator_redis
Project-URL: Documentation, https://gitee.com/sky_flash/llm_repeator_redis/docs
Classifier: Programming Language :: Python :: 3
Classifier: Programming Language :: Python :: 3.10
Classifier: Programming Language :: Python :: 3.11
Classifier: Programming Language :: Python :: 3.12
Classifier: Operating System :: OS Independent
Requires-Python: >=3.10
Requires-Dist: certifi>=2025.1.31
Requires-Dist: Jinja2<4.0.0,>=3.1.6
Requires-Dist: langchain_core<0.4.0,>=0.3.65
Requires-Dist: langchain_deepseek<0.2.0,>=0.1.3
Requires-Dist: langchain_ollama<0.4.0,>=0.3.3
Requires-Dist: ollama<0.6.0,>=0.5.1
Requires-Dist: openai<2.0.0,>=1.86.0
Requires-Dist: pytest<9.0.0,>=8.3.5
Requires-Dist: redis<6.0.0,>=5.2.1
Requires-Dist: Requests<3.0.0,>=2.32.4
Requires-Dist: typing_extensions<5.0.0,>=4.14.0
Requires-Dist: llm_client_redis<0.2.0,>=0.1.9
